Dolar_BC/Dolar_BC.py
Dolar_BC/__init__.py
dolar_bc-1.1.3.dist-info/METADATA
dolar_bc-1.1.3.dist-info/WHEEL
dolar_bc-1.1.3.dist-info/licenses/LICENSE
dolar_bc-1.1.3.dist-info/RECORD
