Metadata-Version: 2.1
Name: Dolar_BC
Version: 1.1.3
Summary: This script has as its objective to offer a pack of functions to work with Dollar, so it can be easily imported into your projects.
Project-URL: Homepage, https://github.com/Joaolpridolficarvalho/Dolar-BC
Project-URL: Bug Tracker, https://github.com/pypa/sampleproject/issues
Author-email: JOAO LUCAS CARVALHO <joao.carvalho43@fatec.sp.gov.br>
License-File: LICENSE
Keywords: BC,BRL,USD,dolar
Classifier: License :: OSI Approved :: MIT License
Classifier: Natural Language :: English
Classifier: Operating System :: OS Independent
Classifier: Programming Language :: Python :: 3
Requires-Python: >=3.7
Requires-Dist: beautifulsoup4==4.11.1
Requires-Dist: requests==2.28.1
